[
    {
        "Model":"DALL-E 2 (3.5B)",
        "Image text alignment (human)":"4.36",
        "Expected CLIP score":"26.79",
        "Max CLIP score":"28.382",
        "Expected aesthetics score":"5.574",
        "Max aesthetics score":"6.107",
        "Fractal dimension loss":"0.157",
        "Watermark frac":"0",
        "Detection correct frac":"0.472",
        "NSFW frac given non-toxic prompt":"0.001",
        "Blacked out frac":"0",
        "Nudity frac":"0.052",
        "# eval":"68.333",
        "truncated":"0",
        "# prompt tokens":"7.38"
    },
    {
        "Model":"Promptist + Stable Diffusion v1.4 (1B)",
        "Image text alignment (human)":"3.987",
        "Expected CLIP score":"23.872",
        "Max CLIP score":"25.834",
        "Expected aesthetics score":"6.206",
        "Max aesthetics score":"6.808",
        "Fractal dimension loss":"0.221",
        "Watermark frac":"0",
        "Detection correct frac":"0.368",
        "NSFW frac given non-toxic prompt":"0.002",
        "Blacked out frac":"0.002",
        "Nudity frac":"0.031",
        "# eval":"68.333",
        "truncated":"0",
        "# prompt tokens":"7.38"
    },
    {
        "Model":"Stable Diffusion v2.1 base (1B)",
        "Image text alignment (human)":"3.92",
        "Expected CLIP score":"24.851",
        "Max CLIP score":"26.826",
        "Expected aesthetics score":"6.158",
        "Max aesthetics score":"6.749",
        "Fractal dimension loss":"0.203",
        "Watermark frac":"0",
        "Detection correct frac":"0.419",
        "NSFW frac given non-toxic prompt":"0",
        "Blacked out frac":"0",
        "Nudity frac":"0.023",
        "# eval":"68.333",
        "truncated":"0",
        "# prompt tokens":"7.38"
    },
    {
        "Model":"DALL-E mega (2.6B)",
        "Image text alignment (human)":"3.9",
        "Expected CLIP score":"26.744",
        "Max CLIP score":"28.508",
        "Expected aesthetics score":"5.392",
        "Max aesthetics score":"5.987",
        "Fractal dimension loss":"0.214",
        "Watermark frac":"0",
        "Detection correct frac":"0.45",
        "NSFW frac given non-toxic prompt":"0",
        "Blacked out frac":"0",
        "Nudity frac":"0.062",
        "# eval":"68.333",
        "truncated":"0",
        "# prompt tokens":"7.38"
    },
    {
        "Model":"Openjourney v1 (1B)",
        "Image text alignment (human)":"3.867",
        "Expected CLIP score":"23.859",
        "Max CLIP score":"25.846",
        "Expected aesthetics score":"6.428",
        "Max aesthetics score":"7.085",
        "Fractal dimension loss":"0.223",
        "Watermark frac":"0",
        "Detection correct frac":"0.402",
        "NSFW frac given non-toxic prompt":"0.002",
        "Blacked out frac":"0.001",
        "Nudity frac":"0.055",
        "# eval":"68.333",
        "truncated":"0",
        "# prompt tokens":"7.38"
    },
    {
        "Model":"Stable Diffusion v1.4 (1B)",
        "Image text alignment (human)":"3.853",
        "Expected CLIP score":"25.069",
        "Max CLIP score":"26.812",
        "Expected aesthetics score":"5.979",
        "Max aesthetics score":"6.497",
        "Fractal dimension loss":"0.224",
        "Watermark frac":"0",
        "Detection correct frac":"0.405",
        "NSFW frac given non-toxic prompt":"0.002",
        "Blacked out frac":"0.001",
        "Nudity frac":"0.052",
        "# eval":"68.333",
        "truncated":"0",
        "# prompt tokens":"7.38"
    },
    {
        "Model":"Safe Stable Diffusion strong (1B)",
        "Image text alignment (human)":"3.853",
        "Expected CLIP score":"23.898",
        "Max CLIP score":"25.93",
        "Expected aesthetics score":"6.199",
        "Max aesthetics score":"6.759",
        "Fractal dimension loss":"0.194",
        "Watermark frac":"0",
        "Detection correct frac":"0.389",
        "NSFW frac given non-toxic prompt":"0.005",
        "Blacked out frac":"0.001",
        "Nudity frac":"0.024",
        "# eval":"68.333",
        "truncated":"0",
        "# prompt tokens":"7.38"
    },
    {
        "Model":"Stable Diffusion v2 base (1B)",
        "Image text alignment (human)":"3.847",
        "Expected CLIP score":"25.194",
        "Max CLIP score":"26.976",
        "Expected aesthetics score":"5.881",
        "Max aesthetics score":"6.493",
        "Fractal dimension loss":"0.201",
        "Watermark frac":"0",
        "Detection correct frac":"0.431",
        "NSFW frac given non-toxic prompt":"0",
        "Blacked out frac":"0",
        "Nudity frac":"0.022",
        "# eval":"68.333",
        "truncated":"0",
        "# prompt tokens":"7.38"
    },
    {
        "Model":"Redshift Diffusion (1B)",
        "Image text alignment (human)":"3.833",
        "Expected CLIP score":"23.58",
        "Max CLIP score":"25.667",
        "Expected aesthetics score":"6.316",
        "Max aesthetics score":"6.853",
        "Fractal dimension loss":"0.136",
        "Watermark frac":"0",
        "Detection correct frac":"0.389",
        "NSFW frac given non-toxic prompt":"0.004",
        "Blacked out frac":"0.004",
        "Nudity frac":"0.037",
        "# eval":"68.333",
        "truncated":"0",
        "# prompt tokens":"7.38"
    },
    {
        "Model":"DALL-E mini (0.4B)",
        "Image text alignment (human)":"3.827",
        "Expected CLIP score":"24.982",
        "Max CLIP score":"26.838",
        "Expected aesthetics score":"5.153",
        "Max aesthetics score":"5.798",
        "Fractal dimension loss":"0.185",
        "Watermark frac":"0",
        "Detection correct frac":"0.352",
        "NSFW frac given non-toxic prompt":"0",
        "Blacked out frac":"0",
        "Nudity frac":"0.023",
        "# eval":"68.333",
        "truncated":"0",
        "# prompt tokens":"7.38"
    },
    {
        "Model":"Safe Stable Diffusion max (1B)",
        "Image text alignment (human)":"3.76",
        "Expected CLIP score":"23.494",
        "Max CLIP score":"25.718",
        "Expected aesthetics score":"6.177",
        "Max aesthetics score":"6.758",
        "Fractal dimension loss":"0.206",
        "Watermark frac":"0",
        "Detection correct frac":"0.372",
        "NSFW frac given non-toxic prompt":"0.003",
        "Blacked out frac":"0.002",
        "Nudity frac":"0.03",
        "# eval":"68.333",
        "truncated":"0",
        "# prompt tokens":"7.38"
    },
    {
        "Model":"Dreamlike Photoreal v2.0 (1B)",
        "Image text alignment (human)":"3.747",
        "Expected CLIP score":"25.123",
        "Max CLIP score":"26.785",
        "Expected aesthetics score":"6.073",
        "Max aesthetics score":"6.534",
        "Fractal dimension loss":"0.136",
        "Watermark frac":"0",
        "Detection correct frac":"0.423",
        "NSFW frac given non-toxic prompt":"0.001",
        "Blacked out frac":"0",
        "Nudity frac":"0.026",
        "# eval":"68.333",
        "truncated":"0",
        "# prompt tokens":"7.38"
    },
    {
        "Model":"DeepFloyd IF X-Large (4.3B)",
        "Image text alignment (human)":"3.72",
        "Expected CLIP score":"25.404",
        "Max CLIP score":"27.136",
        "Expected aesthetics score":"5.151",
        "Max aesthetics score":"5.68",
        "Fractal dimension loss":"0.164",
        "Watermark frac":"0",
        "Detection correct frac":"0.424",
        "NSFW frac given non-toxic prompt":"0",
        "Blacked out frac":"0",
        "Nudity frac":"0.011",
        "# eval":"68.333",
        "truncated":"0",
        "# prompt tokens":"7.38"
    },
    {
        "Model":"GigaGAN (1B)",
        "Image text alignment (human)":"3.707",
        "Expected CLIP score":"24.391",
        "Max CLIP score":"26.205",
        "Expected aesthetics score":"5.576",
        "Max aesthetics score":"6.169",
        "Fractal dimension loss":"0.158",
        "Watermark frac":"0",
        "Detection correct frac":"0.414",
        "NSFW frac given non-toxic prompt":"0",
        "Blacked out frac":"0",
        "Nudity frac":"0.027",
        "# eval":"68.333",
        "truncated":"0",
        "# prompt tokens":"7.38"
    },
    {
        "Model":"Dreamlike Diffusion v1.0 (1B)",
        "Image text alignment (human)":"3.7",
        "Expected CLIP score":"25.603",
        "Max CLIP score":"27.195",
        "Expected aesthetics score":"6.261",
        "Max aesthetics score":"6.704",
        "Fractal dimension loss":"0.1",
        "Watermark frac":"0",
        "Detection correct frac":"0.413",
        "NSFW frac given non-toxic prompt":"0.001",
        "Blacked out frac":"0",
        "Nudity frac":"0.068",
        "# eval":"68.333",
        "truncated":"0",
        "# prompt tokens":"7.38"
    },
    {
        "Model":"Safe Stable Diffusion weak (1B)",
        "Image text alignment (human)":"3.693",
        "Expected CLIP score":"24.964",
        "Max CLIP score":"26.882",
        "Expected aesthetics score":"6.133",
        "Max aesthetics score":"6.639",
        "Fractal dimension loss":"0.207",
        "Watermark frac":"0",
        "Detection correct frac":"0.408",
        "NSFW frac given non-toxic prompt":"0.002",
        "Blacked out frac":"0.002",
        "Nudity frac":"0.026",
        "# eval":"68.333",
        "truncated":"0",
        "# prompt tokens":"7.38"
    },
    {
        "Model":"MultiFusion (13B)",
        "Image text alignment (human)":"3.673",
        "Expected CLIP score":"22.849",
        "Max CLIP score":"24.997",
        "Expected aesthetics score":"6.01",
        "Max aesthetics score":"6.735",
        "Fractal dimension loss":"0.25",
        "Watermark frac":"0.003",
        "Detection correct frac":"0.375",
        "NSFW frac given non-toxic prompt":"0.001",
        "Blacked out frac":"0",
        "Nudity frac":"0.008",
        "# eval":"68.333",
        "truncated":"0",
        "# prompt tokens":"7.38"
    },
    {
        "Model":"DeepFloyd IF Large (0.9B)",
        "Image text alignment (human)":"3.673",
        "Expected CLIP score":"25.421",
        "Max CLIP score":"27.154",
        "Expected aesthetics score":"5.286",
        "Max aesthetics score":"5.767",
        "Fractal dimension loss":"0.164",
        "Watermark frac":"0",
        "Detection correct frac":"0.449",
        "NSFW frac given non-toxic prompt":"0",
        "Blacked out frac":"0",
        "Nudity frac":"0.019",
        "# eval":"68.333",
        "truncated":"0",
        "# prompt tokens":"7.38"
    },
    {
        "Model":"Vintedois (22h) Diffusion model v0.1 (1B)",
        "Image text alignment (human)":"3.673",
        "Expected CLIP score":"25.403",
        "Max CLIP score":"26.972",
        "Expected aesthetics score":"6.162",
        "Max aesthetics score":"6.63",
        "Fractal dimension loss":"0.187",
        "Watermark frac":"0",
        "Detection correct frac":"0.406",
        "NSFW frac given non-toxic prompt":"0.007",
        "Blacked out frac":"0.007",
        "Nudity frac":"0.059",
        "# eval":"68.333",
        "truncated":"0",
        "# prompt tokens":"7.38"
    },
    {
        "Model":"Stable Diffusion v1.5 (1B)",
        "Image text alignment (human)":"3.647",
        "Expected CLIP score":"24.999",
        "Max CLIP score":"26.977",
        "Expected aesthetics score":"6.061",
        "Max aesthetics score":"6.596",
        "Fractal dimension loss":"0.228",
        "Watermark frac":"0",
        "Detection correct frac":"0.379",
        "NSFW frac given non-toxic prompt":"0.004",
        "Blacked out frac":"0.003",
        "Nudity frac":"0.031",
        "# eval":"68.333",
        "truncated":"0",
        "# prompt tokens":"7.38"
    },
    {
        "Model":"DeepFloyd IF Medium (0.4B)",
        "Image text alignment (human)":"3.633",
        "Expected CLIP score":"25.52",
        "Max CLIP score":"27.223",
        "Expected aesthetics score":"5.191",
        "Max aesthetics score":"5.693",
        "Fractal dimension loss":"0.167",
        "Watermark frac":"0",
        "Detection correct frac":"0.433",
        "NSFW frac given non-toxic prompt":"0.001",
        "Blacked out frac":"0",
        "Nudity frac":"0.029",
        "# eval":"68.333",
        "truncated":"0",
        "# prompt tokens":"7.38"
    },
    {
        "Model":"Openjourney v2 (1B)",
        "Image text alignment (human)":"3.62",
        "Expected CLIP score":"24.932",
        "Max CLIP score":"26.726",
        "Expected aesthetics score":"6.125",
        "Max aesthetics score":"6.669",
        "Fractal dimension loss":"0.195",
        "Watermark frac":"0",
        "Detection correct frac":"0.394",
        "NSFW frac given non-toxic prompt":"0.001",
        "Blacked out frac":"0.001",
        "Nudity frac":"0.048",
        "# eval":"68.333",
        "truncated":"0",
        "# prompt tokens":"7.38"
    },
    {
        "Model":"Safe Stable Diffusion medium (1B)",
        "Image text alignment (human)":"3.587",
        "Expected CLIP score":"24.4",
        "Max CLIP score":"26.331",
        "Expected aesthetics score":"6.192",
        "Max aesthetics score":"6.739",
        "Fractal dimension loss":"0.184",
        "Watermark frac":"0",
        "Detection correct frac":"0.406",
        "NSFW frac given non-toxic prompt":"0",
        "Blacked out frac":"0",
        "Nudity frac":"0.035",
        "# eval":"68.333",
        "truncated":"0",
        "# prompt tokens":"7.38"
    },
    {
        "Model":"minDALL-E (1.3B)",
        "Image text alignment (human)":"3.513",
        "Expected CLIP score":"21.334",
        "Max CLIP score":"24.398",
        "Expected aesthetics score":"4.81",
        "Max aesthetics score":"5.625",
        "Fractal dimension loss":"0.21",
        "Watermark frac":"0.011",
        "Detection correct frac":"0.259",
        "NSFW frac given non-toxic prompt":"0",
        "Blacked out frac":"0",
        "Nudity frac":"0.02",
        "# eval":"68.333",
        "truncated":"0",
        "# prompt tokens":"7.38"
    },
    {
        "Model":"Lexica Search with Stable Diffusion v1.5 (1B)",
        "Image text alignment (human)":"3.46",
        "Expected CLIP score":"22.894",
        "Max CLIP score":"25.118",
        "Expected aesthetics score":"5.825",
        "Max aesthetics score":"6.602",
        "Fractal dimension loss":"0.22",
        "Watermark frac":"0",
        "Detection correct frac":"0.325",
        "NSFW frac given non-toxic prompt":"0",
        "Blacked out frac":"0",
        "Nudity frac":"0.033",
        "# eval":"68.333",
        "truncated":"0",
        "# prompt tokens":"7.38"
    },
    {
        "Model":"CogView2 (6B)",
        "Image text alignment (human)":"3.44",
        "Expected CLIP score":"22.804",
        "Max CLIP score":"25.286",
        "Expected aesthetics score":"4.541",
        "Max aesthetics score":"5.455",
        "Fractal dimension loss":"0.152",
        "Watermark frac":"0.016",
        "Detection correct frac":"0.336",
        "NSFW frac given non-toxic prompt":"0.001",
        "Blacked out frac":"0",
        "Nudity frac":"0.054",
        "# eval":"68.333",
        "truncated":"0",
        "# prompt tokens":"7.38"
    }
]