[
    {
        "table_id":17158,
        "row_id":106014,
        "rank":1,
        "method":"PaLI-X",
        "mlmodel":{

        },
        "method_short":"PaLI-X",
        "method_details":null,
        "mlmodel_short":null,
        "mlmodeldetails":null,
        "evaluation_date":"2023-05-29",
        "metrics":{
            "WUPS":"38.3"
        },
        "raw_metrics":{
            "WUPS":38.3
        },
        "uses_additional_data":true,
        "paper":{
            "id":1219485,
            "title":"PaLI-X: On Scaling up a Multilingual Vision and Language Model",
            "url":"\/paper\/pali-x-on-scaling-up-a-multilingual-vision",
            "published":"2023-05-29T00:00:00.000000",
            "code":true,
            "review_url":"\/paper\/pali-x-on-scaling-up-a-multilingual-vision\/review\/?hl=106014"
        },
        "external_source_url":null,
        "tags":[

        ],
        "reports":[

        ]
    },
    {
        "table_id":17158,
        "row_id":110634,
        "rank":2,
        "method":"PaLI-3",
        "mlmodel":{

        },
        "method_short":"PaLI-3",
        "method_details":null,
        "mlmodel_short":null,
        "mlmodeldetails":null,
        "evaluation_date":"2023-10-13",
        "metrics":{
            "WUPS":"37.7"
        },
        "raw_metrics":{
            "WUPS":37.7
        },
        "uses_additional_data":true,
        "paper":{
            "id":1300142,
            "title":"PaLI-3 Vision Language Models: Smaller, Faster, Stronger",
            "url":"\/paper\/pali-3-vision-language-models-smaller-faster",
            "published":"2023-10-13T00:00:00.000000",
            "code":true,
            "review_url":"\/paper\/pali-3-vision-language-models-smaller-faster\/review\/?hl=110634"
        },
        "external_source_url":null,
        "tags":[

        ],
        "reports":[

        ]
    },
    {
        "table_id":17158,
        "row_id":106329,
        "rank":3,
        "method":"R2A",
        "mlmodel":{

        },
        "method_short":"R2A",
        "method_details":null,
        "mlmodel_short":null,
        "mlmodeldetails":null,
        "evaluation_date":"2023-06-15",
        "metrics":{
            "WUPS":"34.7"
        },
        "raw_metrics":{
            "WUPS":34.7
        },
        "uses_additional_data":true,
        "paper":{
            "id":1231633,
            "title":"Retrieving-to-Answer: Zero-Shot Video Question Answering with Frozen Large Language Models",
            "url":"\/paper\/retrieving-to-answer-zero-shot-video-question",
            "published":"2023-06-15T00:00:00.000000",
            "code":false,
            "review_url":null
        },
        "external_source_url":null,
        "tags":[

        ],
        "reports":[

        ]
    },
    {
        "table_id":17158,
        "row_id":53559,
        "rank":4,
        "method":"Flamingo(32-shot)",
        "mlmodel":{

        },
        "method_short":"Flamingo",
        "method_details":"32-shot",
        "mlmodel_short":null,
        "mlmodeldetails":null,
        "evaluation_date":"2022-04-28",
        "metrics":{
            "WUPS":"33.5"
        },
        "raw_metrics":{
            "WUPS":33.5
        },
        "uses_additional_data":true,
        "paper":{
            "id":1001838,
            "title":"Flamingo: a Visual Language Model for Few-Shot Learning",
            "url":"\/paper\/flamingo-a-visual-language-model-for-few-shot-1",
            "published":"2022-04-29T00:00:00.000000",
            "code":true,
            "review_url":null
        },
        "external_source_url":null,
        "tags":[

        ],
        "reports":[

        ]
    },
    {
        "table_id":17158,
        "row_id":106015,
        "rank":5,
        "method":"Flamingo(0-shot)",
        "mlmodel":{

        },
        "method_short":"Flamingo",
        "method_details":"0-shot",
        "mlmodel_short":null,
        "mlmodeldetails":null,
        "evaluation_date":"2022-04-29",
        "metrics":{
            "WUPS":"26.7"
        },
        "raw_metrics":{
            "WUPS":26.7
        },
        "uses_additional_data":true,
        "paper":{
            "id":1001838,
            "title":"Flamingo: a Visual Language Model for Few-Shot Learning",
            "url":"\/paper\/flamingo-a-visual-language-model-for-few-shot-1",
            "published":"2022-04-29T00:00:00.000000",
            "code":true,
            "review_url":null
        },
        "external_source_url":null,
        "tags":[

        ],
        "reports":[

        ]
    },
    {
        "table_id":17158,
        "row_id":106016,
        "rank":6,
        "method":"Emu(0-shot)",
        "mlmodel":{

        },
        "method_short":"Emu",
        "method_details":"0-shot",
        "mlmodel_short":null,
        "mlmodeldetails":null,
        "evaluation_date":"2023-07-11",
        "metrics":{
            "WUPS":"23.4"
        },
        "raw_metrics":{
            "WUPS":23.4
        },
        "uses_additional_data":true,
        "paper":{
            "id":1244202,
            "title":"Generative Pretraining in Multimodality",
            "url":"\/paper\/generative-pretraining-in-multimodality",
            "published":"2023-07-11T00:00:00.000000",
            "code":true,
            "review_url":"\/paper\/generative-pretraining-in-multimodality\/review\/?hl=106016"
        },
        "external_source_url":null,
        "tags":[

        ],
        "reports":[

        ]
    }
]