[
    {
        "table_id":14849,
        "row_id":46639,
        "rank":1,
        "Model":"sammy786\/wav2vec2-xlsr-sakha",
        "mlmodel":{
            "last_updated":"2022-03-24T11:56:16.000000+0000",
            "id":3525,
            "url":null
        },
        "method_short":"sammy786\/wav2vec2-xlsr-sakha",
        "method_details":null,
        "mlmodel_short":"sammy786\/wav2vec2-xlsr-sakha",
        "mlmodeldetails":null,
        "evaluation_date":"2022-02-06",
        "metrics":{
            "Test WER":"36.15%",
            "Test CER":"8.06%"
        },
        "raw_metrics":{
            "Test WER":36.15,
            "Test CER":8.06
        },
        "uses_additional_data":false,
        "paper":{
            "id":null,
            "title":null,
            "url":null,
            "published":null,
            "code":false,
            "review_url":null
        },
        "external_source_url":"https:\/\/huggingface.co\/sammy786\/wav2vec2-xlsr-sakha",
        "tags":[

        ],
        "reports":[

        ]
    },
    {
        "table_id":14849,
        "row_id":49932,
        "rank":2,
        "Model":"wav2vec2-large-xlsr-53-sah-CV8",
        "mlmodel":{
            "last_updated":"2022-03-24T11:53:42.000000+0000",
            "id":3343,
            "url":null
        },
        "method_short":"wav2vec2-large-xlsr-53-sah-CV8",
        "method_details":null,
        "mlmodel_short":"wav2vec2-large-xlsr-53-sah-CV8",
        "mlmodeldetails":null,
        "evaluation_date":"2022-03-23",
        "metrics":{
            "Test WER":"43.75%",
            "Test CER":null
        },
        "raw_metrics":{
            "Test WER":43.75,
            "Test CER":null
        },
        "uses_additional_data":false,
        "paper":{
            "id":null,
            "title":null,
            "url":null,
            "published":null,
            "code":false,
            "review_url":null
        },
        "external_source_url":"https:\/\/huggingface.co\/emre\/wav2vec2-large-xlsr-53-sah-CV8",
        "tags":[

        ],
        "reports":[

        ]
    }
]