[
    {
        "Model":"X3D-M",
        "Data":"S100-PM",
        "Incep.":54.2,
        "Short.":52.0,
        "GFLOPs*views":"4.9*3*10"
    },
    {
        "Model":"X3D-M",
        "Data":"3Massiv",
        "Incep.":53.7,
        "Short.":52.6,
        "GFLOPs*views":"4.9*3*10"
    },
    {
        "Model":"X3D-M",
        "Data":"PM-400",
        "Incep.":61.7,
        "Short.":61.2,
        "GFLOPs*views":"4.9*3*10"
    },
    {
        "Model":"Uniformer-S",
        "Data":"S100-PM",
        "Incep.":39.7,
        "Short.":42.0,
        "GFLOPs*views":"41.8*1*4"
    },
    {
        "Model":"Uniformer-S",
        "Data":"3Massiv",
        "Incep.":42.8,
        "Short.":43.6,
        "GFLOPs*views":"41.8*1*4"
    },
    {
        "Model":"Uniformer-S",
        "Data":"PM-400",
        "Incep.":50.2,
        "Short.":50.4,
        "GFLOPs*views":"64.0*1*5"
    },
    {
        "Model":"MViTv2-S",
        "Data":"S100-PM",
        "Incep.":36.9,
        "Short.":41.0,
        "GFLOPs*views":"64.0*1*5"
    },
    {
        "Model":"MViTv2-S",
        "Data":"3Massiv",
        "Incep.":50.4,
        "Short.":52.1,
        "GFLOPs*views":"64.0*1*5"
    },
    {
        "Model":"MViTv2-S",
        "Data":"PM-400",
        "Incep.":61.7,
        "Short.":62.0,
        "GFLOPs*views":"64.0*1*5"
    }
]