[
    {
        "table_id":4434,
        "row_id":64215,
        "rank":1,
        "method":"GIT2, Single Model",
        "mlmodel":{

        },
        "Model":"GIT2, Single Model",
        "method_details":null,
        "mlmodel_short":null,
        "mlmodeldetails":null,
        "evaluation_date":"2022-08-22",
        "metrics":{
            "CIDEr":"125.51",
            "B1":"88.9",
            "B2":"75.86",
            "B3":"58.9",
            "B4":"38.95",
            "ROUGE-L":"63.66",
            "METEOR":"32.95",
            "SPICE":"16.11"
        },
        "raw_metrics":{
            "CIDEr":125.51,
            "B1":88.9,
            "B2":75.86,
            "B3":58.9,
            "B4":38.95,
            "ROUGE-L":63.66,
            "METEOR":32.95,
            "SPICE":16.11
        },
        "uses_additional_data":false,
        "paper":{
            "id":1017294,
            "title":"GIT: A Generative Image-to-text Transformer for Vision and Language",
            "url":"\/paper\/git-a-generative-image-to-text-transformer",
            "published":"2022-05-27T00:00:00.000000",
            "code":true,
            "review_url":"\/paper\/git-a-generative-image-to-text-transformer\/review\/?hl=64215"
        },
        "external_source_url":"https:\/\/eval.ai\/web\/challenges\/challenge-page\/355\/leaderboard\/1009#leaderboardrank-1",
        "tags":[

        ],
        "reports":[

        ]
    },
    {
        "table_id":4434,
        "row_id":66282,
        "rank":2,
        "method":"PaLI",
        "mlmodel":{

        },
        "Model":"PaLI",
        "method_details":null,
        "mlmodel_short":null,
        "mlmodeldetails":null,
        "evaluation_date":"2022-09-14",
        "metrics":{
            "CIDEr":"124.35",
            "B1":"88.57",
            "B2":"75.56",
            "B3":"58.99",
            "B4":"39.98",
            "ROUGE-L":"63.99",
            "METEOR":"33.47",
            "SPICE":"15.75"
        },
        "raw_metrics":{
            "CIDEr":124.35,
            "B1":88.57,
            "B2":75.56,
            "B3":58.99,
            "B4":39.98,
            "ROUGE-L":63.99,
            "METEOR":33.47,
            "SPICE":15.75
        },
        "uses_additional_data":false,
        "paper":{
            "id":1074922,
            "title":"PaLI: A Jointly-Scaled Multilingual Language-Image Model",
            "url":"\/paper\/pali-a-jointly-scaled-multilingual-language",
            "published":"2022-09-14T00:00:00.000000",
            "code":true,
            "review_url":"\/paper\/pali-a-jointly-scaled-multilingual-language\/review\/?hl=66282"
        },
        "external_source_url":"https:\/\/eval.ai\/web\/challenges\/challenge-page\/355\/leaderboard\/1009#leaderboardrank-2",
        "tags":[

        ],
        "reports":[

        ]
    },
    {
        "table_id":4434,
        "row_id":55630,
        "rank":3,
        "method":"GIT, Single Model",
        "mlmodel":{

        },
        "Model":"GIT, Single Model",
        "method_details":null,
        "mlmodel_short":null,
        "mlmodeldetails":null,
        "evaluation_date":"2022-05-30",
        "metrics":{
            "CIDEr":"123.92",
            "B1":"88.56",
            "B2":"75.48",
            "B3":"58.46",
            "B4":"38.44",
            "ROUGE-L":"63.5",
            "METEOR":"32.86",
            "SPICE":"15.96"
        },
        "raw_metrics":{
            "CIDEr":123.92,
            "B1":88.56,
            "B2":75.48,
            "B3":58.46,
            "B4":38.44,
            "ROUGE-L":63.5,
            "METEOR":32.86,
            "SPICE":15.96
        },
        "uses_additional_data":false,
        "paper":{
            "id":1017294,
            "title":"GIT: A Generative Image-to-text Transformer for Vision and Language",
            "url":"\/paper\/git-a-generative-image-to-text-transformer",
            "published":"2022-05-27T00:00:00.000000",
            "code":true,
            "review_url":"\/paper\/git-a-generative-image-to-text-transformer\/review\/?hl=55630"
        },
        "external_source_url":"https:\/\/eval.ai\/web\/challenges\/challenge-page\/355\/leaderboard\/1009#leaderboardrank-3",
        "tags":[

        ],
        "reports":[

        ]
    },
    {
        "table_id":4434,
        "row_id":54391,
        "rank":4,
        "method":"CoCa - Google Brain",
        "mlmodel":{

        },
        "Model":"CoCa - Google Brain",
        "method_details":null,
        "mlmodel_short":null,
        "mlmodeldetails":null,
        "evaluation_date":"2022-04-21",
        "metrics":{
            "CIDEr":"120.73",
            "B1":"87.53",
            "B2":"74.49",
            "B3":"57.89",
            "B4":"38.92",
            "ROUGE-L":"62.91",
            "METEOR":"32.71",
            "SPICE":"15.54"
        },
        "raw_metrics":{
            "CIDEr":120.73,
            "B1":87.53,
            "B2":74.49,
            "B3":57.89,
            "B4":38.92,
            "ROUGE-L":62.91,
            "METEOR":32.71,
            "SPICE":15.54
        },
        "uses_additional_data":false,
        "paper":{
            "id":null,
            "title":null,
            "url":null,
            "published":null,
            "code":false,
            "review_url":null
        },
        "external_source_url":"https:\/\/eval.ai\/web\/challenges\/challenge-page\/355\/leaderboard\/1009#leaderboardrank-4",
        "tags":[

        ],
        "reports":[

        ]
    },
    {
        "table_id":4434,
        "row_id":44519,
        "rank":5,
        "method":"Microsoft Cognitive Services team",
        "mlmodel":{

        },
        "Model":"Microsoft Cognitive Services team",
        "method_details":null,
        "mlmodel_short":null,
        "mlmodeldetails":null,
        "evaluation_date":"2021-10-26",
        "metrics":{
            "CIDEr":"115.54",
            "B1":"86.48",
            "B2":"72.6",
            "B3":"55.26",
            "B4":"36.31",
            "ROUGE-L":"61.9",
            "METEOR":"31.8",
            "SPICE":"15.06"
        },
        "raw_metrics":{
            "CIDEr":115.54,
            "B1":86.48,
            "B2":72.6,
            "B3":55.26,
            "B4":36.31,
            "ROUGE-L":61.9,
            "METEOR":31.8,
            "SPICE":15.06
        },
        "uses_additional_data":false,
        "paper":{
            "id":220000,
            "title":"VIVO: Visual Vocabulary Pre-Training for Novel Object Captioning",
            "url":"\/paper\/vivo-surpassing-human-performance-in-novel",
            "published":"2020-09-28T00:00:00.000000",
            "code":false,
            "review_url":"\/paper\/vivo-surpassing-human-performance-in-novel\/review\/?hl=44519"
        },
        "external_source_url":"https:\/\/eval.ai\/web\/challenges\/challenge-page\/355\/leaderboard\/1009#leaderboardrank-5",
        "tags":[

        ],
        "reports":[

        ]
    },
    {
        "table_id":4434,
        "row_id":38564,
        "rank":6,
        "method":"Single Model",
        "mlmodel":{

        },
        "Model":"Single Model",
        "method_details":null,
        "mlmodel_short":null,
        "mlmodeldetails":null,
        "evaluation_date":"2021-07-18",
        "metrics":{
            "CIDEr":"110.76",
            "B1":"84.36",
            "B2":"69.83",
            "B3":"52.42",
            "B4":"33.74",
            "ROUGE-L":"60.46",
            "METEOR":"30.97",
            "SPICE":"14.61"
        },
        "raw_metrics":{
            "CIDEr":110.76,
            "B1":84.36,
            "B2":69.83,
            "B3":52.42,
            "B4":33.74,
            "ROUGE-L":60.46,
            "METEOR":30.97,
            "SPICE":14.61
        },
        "uses_additional_data":false,
        "paper":{
            "id":856712,
            "title":"SimVLM: Simple Visual Language Model Pretraining with Weak Supervision",
            "url":"\/paper\/simvlm-simple-visual-language-model",
            "published":"2021-08-24T00:00:00.000000",
            "code":true,
            "review_url":"\/paper\/simvlm-simple-visual-language-model\/review\/?hl=38564"
        },
        "external_source_url":"https:\/\/eval.ai\/web\/challenges\/challenge-page\/355\/leaderboard\/1009#leaderboardrank-6",
        "tags":[

        ],
        "reports":[

        ]
    }
]