[
    {
        "Model":"ACROSS Model V2",
        "Created":"05\/27\/2023",
        "Accuracy":0.915
    },
    {
        "Model":"proton",
        "Created":"10\/28\/2022",
        "Accuracy":0.9083
    },
    {
        "Model":"UL Test",
        "Created":"03\/14\/2022",
        "Accuracy":0.9071
    },
    {
        "Model":"piqa",
        "Created":"10\/28\/2022",
        "Accuracy":0.9057
    },
    {
        "Model":"commonsense",
        "Created":"10\/28\/2022",
        "Accuracy":0.9042
    },
    {
        "Model":"anonymous",
        "Created":"10\/25\/2022",
        "Accuracy":0.9019
    },
    {
        "Model":"Commonsense Verifier + Unicorn (ensemble)",
        "Created":"04\/13\/2023",
        "Accuracy":0.9013
    },
    {
        "Model":"UNICORN",
        "Created":"07\/24\/2020",
        "Accuracy":0.9013
    },
    {
        "Model":"anonymous",
        "Created":"10\/17\/2022",
        "Accuracy":0.8987
    },
    {
        "Model":"anonymous",
        "Created":"11\/23\/2022",
        "Accuracy":0.8967
    },
    {
        "Model":"UnifiedQA (T5-11B) - finetuned",
        "Created":"10\/05\/2020",
        "Accuracy":0.895
    },
    {
        "Model":"PaLM Zero-shot CoT",
        "Created":"10\/29\/2023",
        "Accuracy":0.8862
    },
    {
        "Model":"DeBERTa Large",
        "Created":"06\/03\/2022",
        "Accuracy":0.8741
    },
    {
        "Model":"DeBERTa Large",
        "Created":"05\/03\/2022",
        "Accuracy":0.859
    },
    {
        "Model":"Anonymous",
        "Created":"11\/11\/2021",
        "Accuracy":0.854
    },
    {
        "Model":"UnifiedQA (T5-3B) - finetuned",
        "Created":"05\/26\/2020",
        "Accuracy":0.8526
    },
    {
        "Model":"Anonymous",
        "Created":"11\/11\/2021",
        "Accuracy":0.8506
    },
    {
        "Model":"Anonymous",
        "Created":"11\/11\/2021",
        "Accuracy":0.8506
    },
    {
        "Model":"UnifiedQA-3b + Structured Knowledge",
        "Created":"01\/25\/2022",
        "Accuracy":0.8497
    },
    {
        "Model":"DeBERTa-MTL",
        "Created":"04\/19\/2022",
        "Accuracy":0.8082
    },
    {
        "Model":"Roberta Ensemble - Large",
        "Created":"07\/15\/2020",
        "Accuracy":0.7966
    },
    {
        "Model":"RoBERTa Large Finetuning",
        "Created":"11\/19\/2019",
        "Accuracy":0.794
    },
    {
        "Model":"Albert + KG",
        "Created":"05\/26\/2020",
        "Accuracy":0.7928
    },
    {
        "Model":"Roberta Ensemble",
        "Created":"07\/01\/2020",
        "Accuracy":0.7908
    },
    {
        "Model":"RoBERTa w. CNQA",
        "Created":"12\/02\/2019",
        "Accuracy":0.7853
    },
    {
        "Model":"HighOrderGN + RoBERTa",
        "Created":"01\/15\/2020",
        "Accuracy":0.7838
    },
    {
        "Model":"McQueen + RoBerta",
        "Created":"12\/03\/2019",
        "Accuracy":0.7824
    },
    {
        "Model":"Roberta Finetuned",
        "Created":"07\/15\/2021",
        "Accuracy":0.7818
    },
    {
        "Model":"Roberta + knowledge",
        "Created":"10\/31\/2021",
        "Accuracy":0.7702
    },
    {
        "Model":"Anony",
        "Created":"05\/03\/2022",
        "Accuracy":0.7455
    },
    {
        "Model":"piqa team roberta lr1e-6 epoch6 valacc75.79",
        "Created":"03\/08\/2023",
        "Accuracy":0.7353
    },
    {
        "Model":"McQueen PhysicalIQA + BERTv2",
        "Created":"09\/05\/2019",
        "Accuracy":0.7228
    },
    {
        "Model":"McQueen PhysicalIQA + BERT",
        "Created":"09\/05\/2019",
        "Accuracy":0.7215
    },
    {
        "Model":"GPT",
        "Created":"06\/20\/2019",
        "Accuracy":0.6923
    },
    {
        "Model":"anonymous",
        "Created":"06\/16\/2023",
        "Accuracy":0.6767
    },
    {
        "Model":"Test",
        "Created":"09\/04\/2022",
        "Accuracy":0.6709
    },
    {
        "Model":"BERT Large Finetuning",
        "Created":"11\/19\/2019",
        "Accuracy":0.6666
    },
    {
        "Model":"UQA-large",
        "Created":"09\/05\/2022",
        "Accuracy":0.655
    }
]