[
    {
        "table_id":25537,
        "row_id":111641,
        "rank":1,
        "method":"ATHENA (roberta-large)",
        "mlmodel":{

        },
        "method_short":"ATHENA ",
        "method_details":"roberta-large",
        "mlmodel_short":null,
        "mlmodeldetails":null,
        "evaluation_date":"2023-11-02",
        "metrics":{
            "Execution Accuracy":"91"
        },
        "raw_metrics":{
            "Execution Accuracy":91.0
        },
        "uses_additional_data":false,
        "paper":{
            "id":1313161,
            "title":"ATHENA: Mathematical Reasoning with Thought Expansion",
            "url":"\/paper\/athena-mathematical-reasoning-with-thought",
            "published":"2023-11-02T00:00:00.000000",
            "code":true,
            "review_url":"\/paper\/athena-mathematical-reasoning-with-thought\/review\/?hl=111641"
        },
        "external_source_url":null,
        "tags":[

        ],
        "reports":[

        ]
    },
    {
        "table_id":25537,
        "row_id":111637,
        "rank":2,
        "method":"ATHENA (roberta-base)",
        "mlmodel":{

        },
        "method_short":"ATHENA ",
        "method_details":"roberta-base",
        "mlmodel_short":null,
        "mlmodeldetails":null,
        "evaluation_date":"2023-11-02",
        "metrics":{
            "Execution Accuracy":"86.4"
        },
        "raw_metrics":{
            "Execution Accuracy":86.4
        },
        "uses_additional_data":false,
        "paper":{
            "id":1313161,
            "title":"ATHENA: Mathematical Reasoning with Thought Expansion",
            "url":"\/paper\/athena-mathematical-reasoning-with-thought",
            "published":"2023-11-02T00:00:00.000000",
            "code":true,
            "review_url":"\/paper\/athena-mathematical-reasoning-with-thought\/review\/?hl=111637"
        },
        "external_source_url":null,
        "tags":[

        ],
        "reports":[

        ]
    },
    {
        "table_id":25537,
        "row_id":111651,
        "rank":3,
        "method":"Graph2Tree with RoBERTa",
        "mlmodel":{

        },
        "method_short":"Graph2Tree with RoBERTa",
        "method_details":null,
        "mlmodel_short":null,
        "mlmodeldetails":null,
        "evaluation_date":"2021-03-12",
        "metrics":{
            "Execution Accuracy":"82.2"
        },
        "raw_metrics":{
            "Execution Accuracy":82.2
        },
        "uses_additional_data":false,
        "paper":{
            "id":753666,
            "title":"Are NLP Models really able to Solve Simple Math Word Problems?",
            "url":"\/paper\/are-nlp-models-really-able-to-solve-simple",
            "published":"2021-03-12T00:00:00.000000",
            "code":true,
            "review_url":"\/paper\/are-nlp-models-really-able-to-solve-simple\/review\/?hl=111651"
        },
        "external_source_url":null,
        "tags":[

        ],
        "reports":[

        ]
    },
    {
        "table_id":25537,
        "row_id":111649,
        "rank":4,
        "method":"GTS with RoBERTa",
        "mlmodel":{

        },
        "method_short":"GTS with RoBERTa",
        "method_details":null,
        "mlmodel_short":null,
        "mlmodeldetails":null,
        "evaluation_date":"2021-03-12",
        "metrics":{
            "Execution Accuracy":"81.2"
        },
        "raw_metrics":{
            "Execution Accuracy":81.2
        },
        "uses_additional_data":false,
        "paper":{
            "id":753666,
            "title":"Are NLP Models really able to Solve Simple Math Word Problems?",
            "url":"\/paper\/are-nlp-models-really-able-to-solve-simple",
            "published":"2021-03-12T00:00:00.000000",
            "code":true,
            "review_url":"\/paper\/are-nlp-models-really-able-to-solve-simple\/review\/?hl=111649"
        },
        "external_source_url":null,
        "tags":[

        ],
        "reports":[

        ]
    },
    {
        "table_id":25537,
        "row_id":111647,
        "rank":5,
        "method":"LSTM Seq2Seq with RoBERTa",
        "mlmodel":{

        },
        "method_short":"LSTM Seq2Seq with RoBERTa",
        "method_details":null,
        "mlmodel_short":null,
        "mlmodeldetails":null,
        "evaluation_date":"2021-03-12",
        "metrics":{
            "Execution Accuracy":"76.9"
        },
        "raw_metrics":{
            "Execution Accuracy":76.9
        },
        "uses_additional_data":false,
        "paper":{
            "id":753666,
            "title":"Are NLP Models really able to Solve Simple Math Word Problems?",
            "url":"\/paper\/are-nlp-models-really-able-to-solve-simple",
            "published":"2021-03-12T00:00:00.000000",
            "code":true,
            "review_url":"\/paper\/are-nlp-models-really-able-to-solve-simple\/review\/?hl=111647"
        },
        "external_source_url":null,
        "tags":[

        ],
        "reports":[

        ]
    }
]